{
    "config": {
        "delay-time-before-end": 3000,
        "max-action-page-tries": 10
    },
    "navigation": [
        {
            "type": "page",
            "url": "https://www.google.com",
            "delay-time-before-next": 100,
            "elements": [
                {
                    "type": "dom-element",
                    "id": null,
                    "name": null,
                    "xpath": "//div[@class='k1zIA rSk4se']",
                    "actions": [
                        {
                            "type": "node-screenshot",
                            "output-base-file-name": "<SCREENSHOT_BASE_NAME>",
                            "delay-time-before-next": 100
                        }
                    ]
                }
            ]
        }
    ]
}