{
    "config": {
        "only-validate-config-files": false,
        "delay-time-before-end": 3000,
        "max-action-page-tries": 2
    },
    "navigation": [
        {
            "type": "page",
            "url": "https://www.google.com.co/search?q=facebook",
            "delay-time-before-next": 100,
            "elements": [
                {
                    "type": "dom-element",
                    "id": null,
                    "name": null,
                    "xpath": "//body",
                    "actions": [
                        {
                            "type": "navigate",
                            "url": "https://www.gmail.com",
                            "timeout": 30000,
                            "delay-time-before-next": 100
                        }
                    ]
                }
            ]
        }
    ]
}